gcshttpx/__init__.py
gcshttpx/auth.py
gcshttpx/py.typed
gcshttpx/storage.py
gcshttpx-0.1.6.dist-info/METADATA
gcshttpx-0.1.6.dist-info/WHEEL
gcshttpx-0.1.6.dist-info/licenses/LICENSE
gcshttpx-0.1.6.dist-info/RECORD
