Metadata-Version: 2.4
Name: gcshttpx
Version: 0.1.6
Summary: Minimal async Google Cloud Storage + Auth client built on httpx (HTTP/2).
Project-URL: Homepage, https://github.com/piotrpenar/gcshttpx
Project-URL: Source, https://github.com/piotrpenar/gcshttpx
Project-URL: Issues, https://github.com/piotrpenar/gcshttpx/issues
Author: Piotr Penar
License: MIT
License-File: LICENSE
Keywords: asyncio,gcs,google-cloud-storage,http2,httpx
Classifier: Development Status :: 4 - Beta
Classifier: Intended Audience :: Developers
Classifier: License :: OSI Approved :: MIT License
Classifier: Programming Language :: Python
Classifier: Programming Language :: Python :: 3
Classifier: Programming Language :: Python :: 3.10
Classifier: Programming Language :: Python :: 3.11
Classifier: Programming Language :: Python :: 3.12
Classifier: Topic :: Internet :: WWW/HTTP
Classifier: Typing :: Typed
Requires-Python: >=3.10
Requires-Dist: cryptography>=43.0.0
Requires-Dist: httpx[http2]>=0.27.0
Requires-Dist: orjson>=3.10.0
Requires-Dist: pyjwt>=2.9.0
Provides-Extra: test
Requires-Dist: coverage>=7.6.0; extra == 'test'
Requires-Dist: pytest-asyncio>=0.23.0; extra == 'test'
Requires-Dist: pytest>=8.0.0; extra == 'test'
